doc/api/api_index.rst
doc/api/generalized.rst
doc/api/generic.rst
doc/api/kopt.rst
doc/api/orthogonal.rst
doc/api/permutation.rst
doc/api/rotational.rst
doc/api/softassign.rst
doc/api/symmetric.rst
doc/api/utils.rst
doc/notebooks/Atom_Atom_Mapping.ipynb
doc/notebooks/Chemical_Structure_Alignment.ipynb
doc/notebooks/Chirality_Check.ipynb
doc/notebooks/Quick_Start.ipynb
doc/notebooks/Ranking_by_Reordering.ipynb
doc/notebooks/notebook_data/atom_atom_mapping/atom_atom_mapping.png
doc/notebooks/notebook_data/chemical_strcuture_alignment/2hhb.pdb
doc/notebooks/notebook_data/chemical_strcuture_alignment/protein_alignment.png
doc/notebooks/notebook_data/chirality_checking/chirality_checking.png
doc/notebooks/notebook_data/chirality_checking/enantiomer1.xyz
doc/notebooks/notebook_data/chirality_checking/enantiomer2.xyz
doc/notebooks/notebook_data/ranking_reordering/ranking.png
procrustes/__init__.py
procrustes/generalized.py
procrustes/generic.py
procrustes/kopt.py
procrustes/orthogonal.py
procrustes/permutation.py
procrustes/psdp.py
procrustes/rotational.py
procrustes/softassign.py
procrustes/symmetric.py
procrustes/utils.py
procrustes/test/__init__.py
procrustes/test/common.py
procrustes/test/test_generalized.py
procrustes/test/test_generic.py
procrustes/test/test_kopt.py
procrustes/test/test_orthogonal.py
procrustes/test/test_permutation.py
procrustes/test/test_psdp.py
procrustes/test/test_rotational.py
procrustes/test/test_softassign.py
procrustes/test/test_symmetric.py
procrustes/test/test_utils.py
qc_procrustes-1.1.2.dist-info/licenses/LICENSE
qc_procrustes-1.1.2.dist-info/METADATA
qc_procrustes-1.1.2.dist-info/WHEEL
qc_procrustes-1.1.2.dist-info/top_level.txt
qc_procrustes-1.1.2.dist-info/zip-safe
qc_procrustes-1.1.2.dist-info/RECORD
