Metadata-Version: 2.4
Name: qc-procrustes
Version: 1.1.2
Summary: Python library for finding the optimal transformation(s) that makes two matrices as close as possible to each other.
Author-email: QC-Devs Community <qcdevs@gmail.com>
License:                     GNU GENERAL PUBLIC LICENSE
Project-URL: homepage, https://github.com/theochem/procrustes
Project-URL: documentation, https://procrustes.qcdevs.org/
Project-URL: repository, https://github.com/theochem/procrustes/
Keywords: procrustes analysis,statistical shape analysis,qudratic assignment problem,matrix transformation,generalized procrustes analysis,orthogonal procrustes problem,symmetric procrustes problem,rotational procrustes problem,permutation procrustes problem,softassign method,molecule alignment,chemical structure similarity
Platform: Linux
Platform: Windows
Platform: MacOS
Classifier: Development Status :: 5 - Production/Stable
Classifier: Environment :: Console
Classifier: License :: OSI Approved :: GNU General Public License v3 (GPLv3)
Classifier: Natural Language :: English
Classifier: Operating System :: MacOS
Classifier: Operating System :: Microsoft :: Windows
Classifier: Operating System :: Unix
Classifier: Operating System :: POSIX
Classifier: Operating System :: POSIX :: Linux
Classifier: Programming Language :: Python
Classifier: Programming Language :: Python :: 3
Classifier: Programming Language :: Python :: 3.9
Classifier: Programming Language :: Python :: 3.10
Classifier: Programming Language :: Python :: 3.11
Classifier: Programming Language :: Python :: 3.12
Classifier: Topic :: Scientific/Engineering
Classifier: Topic :: Scientific/Engineering :: Mathematics
Classifier: Topic :: Scientific/Engineering :: Physics
Classifier: Topic :: Scientific/Engineering :: Chemistry
Classifier: Intended Audience :: Science/Research
Requires-Python: >=3.9
License-File: LICENSE
Requires-Dist: numpy>=1.21.5
Requires-Dist: scipy>=1.9.0
Provides-Extra: dev
Requires-Dist: numpy>=1.21.5; extra == "dev"
Requires-Dist: scipy>=1.9.0; extra == "dev"
Requires-Dist: pytest>=8.3.0; extra == "dev"
Requires-Dist: pytest-cov>=5.0.0; extra == "dev"
Dynamic: license-file
